{
	"type": "minecraft:crafting_shapeless",
	"group": "glossy_block",
	"ingredients": [
		{
			"item": "minecraft:slime_block"
		},
		{
			"item": "minecraft:blue_concrete"
		},
		{
			"item": "minecraft:blue_concrete"
		},
		{
			"item": "minecraft:blue_concrete"
		},
		{
			"item": "minecraft:blue_concrete"
		},
		{
			"item": "minecraft:blue_concrete"
		},
		{
			"item": "minecraft:blue_concrete"
		},
		{
			"item": "minecraft:blue_concrete"
		},
		{
			"item": "minecraft:blue_concrete"
		}
	],
	"result": {
		"item": "redstone_additions:glossy_blue_concrete",
		"count": 8
	}
}
