{
	"type": "minecraft:crafting_shapeless",
	"group": "glossy_block",
	"ingredients": [
		{
			"item": "minecraft:honey_block"
		},
		{
			"item": "minecraft:polished_blackstone"
		},
		{
			"item": "minecraft:polished_blackstone"
		},
		{
			"item": "minecraft:polished_blackstone"
		},
		{
			"item": "minecraft:polished_blackstone"
		},
		{
			"item": "minecraft:polished_blackstone"
		},
		{
			"item": "minecraft:polished_blackstone"
		},
		{
			"item": "minecraft:polished_blackstone"
		},
		{
			"item": "minecraft:polished_blackstone"
		}
	],
	"result": {
		"item": "redstone_additions:glossy_polished_blackstone",
		"count": 8
	}
}
